CHANGELOG.rst
LICENSE
MANIFEST.in
README.rst
setup.py
fn/__init__.py
fn/func.py
fn/iters.py
fn/monad.py
fn/op.py
fn/recur.py
fn/stream.py
fn/underscore.py
fn/uniform.py
fn.py.egg-info/PKG-INFO
fn.py.egg-info/SOURCES.txt
fn.py.egg-info/dependency_links.txt
fn.py.egg-info/not-zip-safe
fn.py.egg-info/top_level.txt
fn/immutable/__init__.py
fn/immutable/finger.py
fn/immutable/heap.py
fn/immutable/list.py
fn/immutable/trie.py