Metadata-Version: 1.1
Name: fn.py
Version: 0.5.0
Summary: 
